ckmeans-0.2.10.dist-info/METADATA
ckmeans-0.2.10.dist-info/WHEEL
ckmeans-0.2.10.dist-info/licenses/license.txt
ckmeans/__init__.py
ckmeans/ckmeans.abi3.so
ckmeans-0.2.10.dist-info/RECORD
