Metadata-Version: 2.4
Name: ckmeans
Version: 0.2.10
Classifier: Programming Language :: Python
Classifier: Programming Language :: Python :: 3.10
Classifier: Programming Language :: Python :: 3.11
Classifier: Programming Language :: Python :: 3.12
Classifier: Programming Language :: Python :: 3.13
Classifier: Development Status :: 5 - Production/Stable
Classifier: Intended Audience :: Science/Research
Classifier: License :: OSI Approved :: Blue Oak Model License (BlueOak-1.0.0)
Classifier: Operating System :: OS Independent
Requires-Dist: pytest>=7.4.2 ; extra == 'test'
Requires-Dist: ckmeans-1d-dp>=4.3.4.4 ; extra == 'test'
Provides-Extra: test
License-File: license.txt
Summary: Optimal univariate (1D) clustering based on Ckmeans.1d.dp
Keywords: ckmeans,clustering,jenks
Author-email: Stephan Hügel <urschrei@gmail.com>
Requires-Python: >=3.10
Project-URL: Repository, https://github.com/urschrei/ckmeans_py
Project-URL: Tracker, https://github.com/urschrei/ckmeans_py/issues
